scripts/__init__.py
scripts/command.py
tests/__init__.py
tests/test_graph_utils.py
vivo_rdflib_sparqlstore-0.4.dist-info/DESCRIPTION.rst
vivo_rdflib_sparqlstore-0.4.dist-info/METADATA
vivo_rdflib_sparqlstore-0.4.dist-info/RECORD
vivo_rdflib_sparqlstore-0.4.dist-info/WHEEL
vivo_rdflib_sparqlstore-0.4.dist-info/entry_points.txt
vivo_rdflib_sparqlstore-0.4.dist-info/metadata.json
vivo_rdflib_sparqlstore-0.4.dist-info/top_level.txt
vstore/__init__.py
vstore/graph_utils.py
vstore/vstore.py
