Metadata-Version: 2.0
Name: vivo-rdflib-sparqlstore
Version: 0.4
Summary: RDFLib SPARQLStore and SPARQLUpdateStore implementation for VIVO.
Home-page: https://github.com/lawlesst/rdflib-vivo-sparqlstore
Author: Ted Lawless
Author-email: lawlesst@gmail.com
License: UNKNOWN
Platform: UNKNOWN
Requires-Python: >=2.7
Requires-Dist: rdflib (>=4.2)
Requires-Dist: SPARQLWrapper (>=1.8)
Requires-Dist: click (>=5.0)
